setup.py
jupyterhub_ldapcreateusers.egg-info/PKG-INFO
jupyterhub_ldapcreateusers.egg-info/SOURCES.txt
jupyterhub_ldapcreateusers.egg-info/dependency_links.txt
jupyterhub_ldapcreateusers.egg-info/requires.txt
jupyterhub_ldapcreateusers.egg-info/top_level.txt
ldapcreateusers/__init__.py
ldapcreateusers/ldapcreateusers.py